{
    "LayerId": "GMU.arlington_2011_address_pnt",
    "Name": "arlington_2011_address_pnt",
    "CollectionId": "geoserver",
    "Institution": "GMU",
    "Access": "Public",
    "DataType": "Point",
    "Availability": "online",
    "LayerDisplayName": "Address Points, Arlington County, VA 2010",
    "Publisher": "GIS Mapping Center",
    "Originator": "GIS Mapping Center, Arlington County, VA",
    "OriginatorSort": "GIS Mapping Center, Arlington County, VA",
    "GeoReferenced": true,
    "Abstract": "Provides a point indicating location of every street number address (excludes suites/apartments/condos or other units) in Arlington County, VA, 2010",
    "Location": "{\"wms\": [\"https://gmutantt.gmu.edu/geoserver/GMUGeodata/wms\"],\"wfs\": \"https://gmutantt.gmu.edu/geoserver/GMUGeodata/wfs\",\"browseGraphic\": \"http://meridian.arlingtonva.local/metadata/images/add_pnt2.jpg\"}",
    "MaxY": 38.9342,
    "MinY": 38.8271,
    "MaxX": -77.0308,
    "MinX": -77.1728,
    "CenterX": -77.1018,
    "CenterY": 38.88065,
    "HalfWidth": 0.07099999999999795,
    "HalfHeight": 0.053549999999997766,
    "Area": 0.015208199999998928,
    "WorkspaceName": "",
    "ContentDate": "2010-01-01 01:01:01+00:00",
    "timestamp": "2020-06-03 18:55:32.737000+00:00",
    "FgdcText": "<?xml version=\"1.0\" encoding=\"UTF-8\" standalone=\"no\"?>\n<metadata>\n  <idinfo>\n    <citation>\n      <citeinfo>\n        <origin>GIS Mapping Center, Arlington County, VA</origin>\n        <pubdate>2010</pubdate>\n        <title>Address Points, Arlington County, VA 2010</title>\n        <geoform>vector digital data</geoform>\n        <pubinfo>\n          <pubplace/>\n          <publish>GIS Mapping Center</publish>\n        </pubinfo>\n      <ftname Sync=\"TRUE\">arlington_2011_address_pnt</ftname>\n</citeinfo>\n    </citation>\n    <descript>\n      <abstract>Provides a point indicating location of every street number address (excludes suites/apartments/condos or other units) in Arlington County, VA, 2010</abstract>\n      <purpose>This dataset is intended for researchers, students, and policy makers for reference and mapping purposes, and may be used for basic applications such as viewing, querying, and map output production, or to provide a base map to support graphical overlays and analysis with other spatial data. </purpose>\n      <supplinf>check STATUS field for information</supplinf>\n    </descript>\n    <timeperd>\n      <timeinfo>\n        <sngdate>\n          <caldate>4/26/2010</caldate>\n        </sngdate>\n      </timeinfo>\n      <current>ground condition</current>\n    </timeperd>\n    <status>\n      <progress>In work</progress>\n      <update>As needed (monthly or more frequently)</update>\n    </status>\n    <spdom>\n      <bounding>\n        <westbc>-77.1728</westbc>\n        <eastbc>-77.0308</eastbc>\n        <northbc>38.9342</northbc>\n        <southbc>38.8271</southbc>\n      </bounding>\n    </spdom>\n    <keywords>\n      <theme>\n        <themekt>Address</themekt>\n        <themekey>Street</themekey>\n        <themekey>Location</themekey>\n      </theme>\n      <place>\n        <placekt>Arlington County</placekt>\n        <placekey>Virginia</placekey>\n        <placekey>VA</placekey>\n      </place>\n    </keywords>\n    <accconst>None, Please see “Distribution Info” for details</accconst>\n    <useconst>1:1200 (1\"=100') and up.</useconst>\n    <ptcontac>\n      <cntinfo>\n        <cntorgp>\n          <cntorg>Arlington County DES GIS Mapping Center</cntorg>\n        </cntorgp>\n        <cntpos>Cartographer </cntpos>\n        <cntaddr>\n          <addrtype>mailing and physical</addrtype>\n          <address>2100 Clarendon Blvd, Suite 813</address>\n          <city>Arlington</city>\n          <state>VA</state>\n          <postal>22201</postal>\n        </cntaddr>\n        <cntvoice>703-228-3629</cntvoice>\n        <cntemail>gismc@arlingtonva.us</cntemail>\n      </cntinfo>\n    </ptcontac>\n    <browse>\n      <browsen>http://meridian.arlingtonva.local/metadata/images/add_pnt2.jpg</browsen>\n      <browset>JPEG</browset>\n      <browsed>Sample of address points labled with STNUM field</browsed>\n    </browse>\n    <native>Microsoft Windows XP Version 5.1 (Build 2600) Service Pack 3; ESRI ArcCatalog 9.3.1.3000</native>\n  </idinfo>\n  <dataqual>\n    <attracc>\n      <attraccr>No formal attribute accuracy tests were conducted.</attraccr>\n    </attracc>\n    <logic>No formal logical accuracy tests were conducted  </logic>\n    <complete>Data set is considered complete for the information presented, as described in the abstract. Users are advised to read the rest of the metadata record carefully for additional details.</complete>\n    <posacc>\n      <horizpa>\n        <horizpar>Point must be within boundaries of property at a minimum but should be within limits of appropriate structures.</horizpar>\n      </horizpa>\n      <vertacc>\n        <vertaccr>A formal accuracy assessment of the vertical positional information in the data set has either not been conducted, or is not applicable.</vertaccr>\n      </vertacc>\n    </posacc>\n    <lineage>\n      <srcinfo>\n        <srccite>\n          <citeinfo>\n            <origin>Permits Plus (CPHD), others</origin>\n            <pubdate>1999</pubdate>\n            <title>Permit System</title>\n            <geoform>Digital tabular data</geoform>\n          </citeinfo>\n        </srccite>\n        <srcscale>NA</srcscale>\n        <typesrc>Digital and/or Hardcopy</typesrc>\n        <srctime>\n          <timeinfo>\n            <sngdate>\n              <caldate/>\n            </sngdate>\n          </timeinfo>\n          <srccurr/>\n        </srctime>\n        <srccitea/>\n        <srccontr/>\n      </srcinfo>\n      <procstep>\n        <procdesc>Dataset copied from the cd obtained from Arlington County, 2011</procdesc>\n        <procdate>Unknown</procdate>\n      </procstep>\n    </lineage>\n  </dataqual>\n  <spdoinfo>\n    <direct>Vector</direct>\n    <ptvctinf>\n      <sdtsterm>\n        <sdtstype>Entity point</sdtstype>\n        <ptvctcnt>42693</ptvctcnt>\n      </sdtsterm>\n    </ptvctinf>\n  </spdoinfo>\n  <spref>\n    <horizsys>\n      <planar>\n        <gridsys>\n          <gridsysn>State Plane Coordinate System 1983</gridsysn>\n          <spcs>\n            <spcszone>4501</spcszone>\n            <lambertc>\n              <stdparll>38.03333333333333</stdparll>\n              <stdparll>39.2</stdparll>\n              <longcm>-78.5</longcm>\n              <latprjo>0.0</latprjo>\n              <feast>11482916.66666666</feast>\n              <fnorth>6561666.666666666</fnorth>\n            </lambertc>\n          </spcs>\n        </gridsys>\n        <planci>\n          <plance>coordinate pair</plance>\n          <coordrep>\n            <absres>0.6096</absres>\n            <ordres>0.6096</ordres>\n          </coordrep>\n          <plandu>survey feet</plandu>\n        </planci>\n      </planar>\n      <geodetic>\n        <horizdn>North_American_Datum_1983</horizdn>\n        <ellips>GRS_1980</ellips>\n        <semiaxis>6378137.0</semiaxis>\n        <denflat>298.257222101</denflat>\n      </geodetic>\n    </horizsys>\n  </spref>\n  <eainfo>\n    <detailed>\n      <enttyp>\n        <enttypl>Address_pnt.shp Attribute Table</enttypl>\n        <enttypd>Table containing attribute information associated with the data set.</enttypd>\n        <enttypds>Producer Defined</enttypds>\n      </enttyp>\n      <attr>\n        <attrlabl>FID</attrlabl>\n        <attrdef>Internal feature number.</attrdef>\n        <attrdefs>ESRI</attrdefs>\n        <attrdomv>\n          <udom>Sequential unique whole numbers that are automatically generated.</udom>\n        </attrdomv>\n      </attr>\n      <attr>\n        <attrlabl>Shape</attrlabl>\n        <attrdef>Feature geometry.</attrdef>\n        <attrdefs>ESRI</attrdefs>\n        <attrdomv>\n<udom>Coordinates defining the features.</udom>\n        </attrdomv>\n      </attr>\n      <attr>\n        <attrlabl>STNUM</attrlabl>\n        <attrdef/>\n        <attrdefs>Producer Defined</attrdefs>\n        <attrdomv>\n<rdom>\n            <rdommin>1</rdommin>\n            <rdommax>7109</rdommax>\n          </rdom>\n        </attrdomv>\n      </attr>\n      <attr>\n        <attrlabl>STCODE</attrlabl>\n        <attrdef/>\n        <attrdefs>Producer Defined</attrdefs>\n        <attrdomv>\n<udom/>\n        </attrdomv>\n      </attr>\n      <attr>\n  <attrlabl>STRTDIR</attrlabl>\n<attrdef/>\n<attrdefs>Producer Defined</attrdefs>\n<attrdomv>\n<edom>\n  <edomv>&lt;&lt; empty cell &gt;&gt;</edomv>\n  <edomvd>\n  </edomvd>\n  <edomvds>Producer defined</edomvds>\n</edom>\n</attrdomv>\n<attrdomv>\n    <edom>\n      <edomv>N</edomv>\n      <edomvd>\n      </edomvd>\n      <edomvds>Producer defined</edomvds>\n    </edom>\n  </attrdomv>\n  <attrdomv>\n    <edom>\n      <edomv>S</edomv>\n      <edomvd>\n      </edomvd>\n      <edomvds>Producer defined</edomvds>\n    </edom>\n  </attrdomv>\n</attr>\n      <attr>\n  <attrlabl>STRTDIRPRE</attrlabl>\n<attrdef/>\n<attrdefs>Producer Defined</attrdefs>\n<attrdomv>\n<edom>\n  <edomv>&lt;&lt; empty cell &gt;&gt;</edomv>\n  <edomvd>\n  </edomvd>\n  <edomvds>Producer defined</edomvds>\n</edom>\n</attrdomv>\n<attrdomv>\n    <edom>\n      <edomv>N</edomv>\n      <edomvd>\n      </edomvd>\n      <edomvds>Producer defined</edomvds>\n    </edom>\n  </attrdomv>\n  <attrdomv>\n    <edom>\n      <edomv>S</edomv>\n      <edomvd>\n      </edomvd>\n      <edomvds>Producer defined</edomvds>\n    </edom>\n  </attrdomv>\n</attr>\n      <attr>\n        <attrlabl>STRTNAME</attrlabl>\n        <attrdef/>\n        <attrdefs>Producer Defined</attrdefs>\n        <attrdomv>\n<udom/>\n        </attrdomv>\n      </attr>\n      <attr>\n  <attrlabl>STRTTYPE</attrlabl>\n<attrdef/>\n<attrdefs>Producer Defined</attrdefs>\n<attrdomv>\n    <edom>\n      <edomv>ST</edomv>\n      <edomvd>\n      </edomvd>\n      <edomvds>Producer defined</edomvds>\n    </edom>\n  </attrdomv>\n  <attrdomv>\n    <edom>\n      <edomv>RD</edomv>\n      <edomvd>\n      </edomvd>\n      <edomvds>Producer defined</edomvds>\n    </edom>\n  </attrdomv>\n  <attrdomv>\n    <edom>\n      <edomv>PL</edomv>\n      <edomvd>\n      </edomvd>\n      <edomvds>Producer defined</edomvds>\n    </edom>\n  </attrdomv>\n  <attrdomv>\n    <edom>\n      <edomv>CT</edomv>\n      <edomvd>\n      </edomvd>\n      <edomvds>Producer defined</edomvds>\n    </edom>\n  </attrdomv>\n  <attrdomv>\n    <edom>\n      <edomv>TER</edomv>\n      <edomvd>\n      </edomvd>\n      <edomvds>Producer defined</edomvds>\n    </edom>\n  </attrdomv>\n  <attrdomv>\n    <edom>\n      <edomv>DR</edomv>\n      <edomvd>\n      </edomvd>\n      <edomvds>Producer defined</edomvds>\n    </edom>\n  </attrdomv>\n  <attrdomv>\n    <edom>\n      <edomv>CIR</edomv>\n      <edomvd>\n      </edomvd>\n      <edomvds>Producer defined</edomvds>\n    </edom>\n  </attrdomv>\n  <attrdomv>\n    <edom>\n      <edomv>AVE</edomv>\n      <edomvd>\n      </edomvd>\n      <edomvds>Producer defined</edomvds>\n    </edom>\n  </attrdomv>\n  <attrdomv>\n    <edom>\n      <edomv>BLVD</edomv>\n      <edomvd>\n      </edomvd>\n      <edomvds>Producer defined</edomvds>\n    </edom>\n  </attrdomv>\n  <attrdomv>\n    <edom>\n      <edomv>PIKE</edomv>\n      <edomvd>\n      </edomvd>\n      <edomvds>Producer defined</edomvds>\n    </edom>\n  </attrdomv>\n  <attrdomv>\n    <edom>\n      <edomv>HWY</edomv>\n      <edomvd>\n      </edomvd>\n      <edomvds>Producer defined</edomvds>\n    </edom>\n  </attrdomv>\n  <attrdomv>\n    <edom>\n      <edomv>LN</edomv>\n      <edomvd>\n      </edomvd>\n      <edomvds>Producer defined</edomvds>\n    </edom>\n  </attrdomv>\n  <attrdomv>\n    <edom>\n      <edomv>ARC</edomv>\n      <edomvd>\n      </edomvd>\n      <edomvds>Producer defined</edomvds>\n    </edom>\n  </attrdomv>\n  <attrdomv>\n    <edom>\n      <edomv>PKWY</edomv>\n      <edomvd>\n      </edomvd>\n      <edomvds>Producer defined</edomvds>\n    </edom>\n  </attrdomv>\n</attr>\n      <attr>\n  <attrlabl>STRTDIRSUF</attrlabl>\n<attrdef/>\n<attrdefs>Producer Defined</attrdefs>\n<attrdomv>\n<edom>\n  <edomv>&lt;&lt; empty cell &gt;&gt;</edomv>\n  <edomvd>\n  </edomvd>\n  <edomvds>Producer defined</edomvds>\n</edom>\n</attrdomv>\n<attrdomv>\n    <edom>\n      <edomv>S</edomv>\n      <edomvd>\n      </edomvd>\n      <edomvds>Producer defined</edomvds>\n    </edom>\n  </attrdomv>\n  <attrdomv>\n    <edom>\n      <edomv>N</edomv>\n      <edomvd>\n      </edomvd>\n      <edomvds>Producer defined</edomvds>\n    </edom>\n  </attrdomv>\n</attr>\n      <attr>\n        <attrlabl>FULL_ADDRE</attrlabl>\n        <attrdef/>\n        <attrdefs>Producer Defined</attrdefs>\n        <attrdomv>\n<udom/>\n        </attrdomv>\n      </attr>\n      <attr>\n  <attrlabl>STATUS</attrlabl>\n<attrdef/>\n<attrdefs>Producer Defined</attrdefs>\n<attrdomv>\n    <edom>\n      <edomv>VERIFIED</edomv>\n      <edomvd>\n      </edomvd>\n      <edomvds>Producer defined</edomvds>\n    </edom>\n  </attrdomv>\n  <attrdomv>\n    <edom>\n      <edomv>FIELD CHECK</edomv>\n      <edomvd>\n      </edomvd>\n      <edomvds>Producer defined</edomvds>\n    </edom>\n  </attrdomv>\n</attr>\n      <attr>\n        <attrlabl>UNITCOUNT</attrlabl>\n        <attrdef/>\n        <attrdefs>Producer Defined</attrdefs>\n        <attrdomv>\n<rdom>\n            <rdommin>0.0</rdommin>\n            <rdommax>560.0</rdommax>\n          </rdom>\n        </attrdomv>\n      </attr>\n      <attr>\n        <attrlabl>STNAME</attrlabl>\n        <attrdef/>\n        <attrdefs>Producer Defined</attrdefs>\n        <attrdomv>\n<udom/>\n        </attrdomv>\n      </attr>\n      <attr>\n        <attrlabl>UNIT</attrlabl>\n        <attrdef/>\n        <attrdefs>Producer Defined</attrdefs>\n        <attrdomv>\n<udom/>\n        </attrdomv>\n      </attr>\n      <attr>\n        <attrlabl>UPDATE_DAT</attrlabl>\n        <attrdef/>\n        <attrdefs>Producer Defined</attrdefs>\n        <attrdomv>\n<udom/>\n        </attrdomv>\n      </attr>\n      <attr>\n        <attrlabl>ZIP5</attrlabl>\n        <attrdef/>\n        <attrdefs>Producer Defined</attrdefs>\n        <attrdomv>\n<rdom>\n            <rdommin>0</rdommin>\n            <rdommax>22213</rdommax>\n          </rdom>\n        </attrdomv>\n      </attr>\n    </detailed>\n  </eainfo>\n  <distinfo>\n    <distrib>\n      <cntinfo>\n        <cntperp>\n          <cntper>George Mason University Libraries</cntper>\n          <cntorg>Digital Scholarship Center</cntorg>\n        </cntperp>\n        <cntaddr>\n          <addrtype>mailing and physical</addrtype>\n          <address>4400 University Drive</address>\n          <city>Fairfax </city>\n          <state>VA</state>\n          <postal>22030</postal>\n        </cntaddr>\n        <cntvoice>703-993-2240</cntvoice>\n        <cntemail>datahelp@gmu.edu</cntemail>\n      </cntinfo>\n    </distrib>\n    <resdesc Sync=\"TRUE\">Downloadable Data</resdesc>\n    <distliab>Distributor assumes no liability for misuse of data</distliab>\n    <stdorder>\n      <digform>\n<digtinfo>\n          <formname>Digital Data</formname>\n        </digtinfo>\n        <digtopt>\n<onlinopt>\n<computer>\n<networka>\n<networkr/>\n</networka>\n</computer>\n</onlinopt>\n</digtopt>\n</digform>\n      <fees>No fees are applicable for obtaining the data set.</fees>\n    </stdorder>\n  </distinfo>\n  <metainfo>\n    <metd>20200510</metd>\n    <metc>\n      <cntinfo>\n        <cntorgp>\n          <cntorg>George Mason University Libraries</cntorg>\n          <cntper>Digital Scholarship Center</cntper>\n        </cntorgp>\n        <cntaddr>\n          <addrtype>mailing and physical</addrtype>\n          <address>4400 University Drive</address>\n          <city>Fairfax </city>\n          <state>VA </state>\n          <postal>22030</postal>\n        </cntaddr>\n        <cntvoice>703-993-2240</cntvoice>\n        <cntemail>datahelp@gmu.edu</cntemail>\n      </cntinfo>\n    </metc>\n    <metstdn>FGDC Content Standards for Digital Geospatial Metadata</metstdn>\n    <metstdv>FGDC-STD-001-1998</metstdv>\n    <mettc Sync=\"TRUE\">local time</mettc>\n  </metainfo>\n</metadata>\n",
    "DataTypeSort": "Point",
    "_version_": 1668505175576281088,
    "LayerDisplayNameSort": "Address Points, Arlington County, VA 2010",
    "PublisherSort": "GIS Mapping Center",
    "InstitutionSort": "GMU",
    "score": 3.55876
}