{
  "dc_publisher_s": "",
  "dc_type_s": "Dataset",
  "dct_title_s": "Census Blocks, Arlington County, VA 2006",
  "dct_description_sm": [
    "This layer represents the annotation for Census Blocks for 1:1200 scale in Arlington County, VA 2006"
  ],
  "schema_provider_s": "GMU",
  "gbl_resourceType_sm": [
    "Polygon"
  ],
  "dct_subject_sm": [
    "Block"
  ],
  "gbl_indexYear_im": [
    2006
  ],
  "locn_geometry": "ENVELOPE(-77.1733, -77.0329, 38.9325, 38.8281)",
  "dct_accessRights_s": "Public",
  "dct_format_s": "Shapefile",
  "gbl_wxsIdentifier_s": ":arlington_2011_block2000_anno_1200",
  "id": "gmu-arlington-2011-block2000-anno-1200",
  "dct_identifier_sm": [
    "GMU.arlington_2011_block2000_anno_1200"
  ],
  "gbl_mdVersion_s": "1.0",
  "dct_temporal_sm": [
    "2006-01-01 01:01:01+00:00"
  ],
  "dct_spatial_sm": [
    "Virginia",
    "VA"
  ],
  "dct_references_s": "{\"http://www.opengis.net/def/serviceType/ogc/wfs\":\"https://gmutantt.gmu.edu/geoserver/GMUGeodata/wfs\",\"http://www.opengis.net/def/serviceType/ogc/wms\":\"https://gmutantt.gmu.edu/geoserver/GMUGeodata/wms\"}"
}