{
  "dc_publisher_s": "",
  "dc_type_s": "Dataset",
  "dct_title_s": "Paved Roads of George Mason University, Fairfax campus, VA 2005",
  "dct_description_sm": [
    "This polygon layer represents the existing 2005 paved roads on Fairfax campus in George Mason University, VA ,"
  ],
  "schema_provider_s": "GMU",
  "gbl_resourceType_sm": [
    "Polygon"
  ],
  "dct_subject_sm": [
    "Transportation"
  ],
  "gbl_indexYear_im": [
    2005
  ],
  "locn_geometry": "ENVELOPE(-77.3117, -77.303, 38.8343, 38.8267)",
  "dct_accessRights_s": "Public",
  "dct_format_s": "Shapefile",
  "gbl_wxsIdentifier_s": ":mason_campus_2005_roads",
  "id": "gmu-mason-campus-2005-roads",
  "dct_identifier_sm": [
    "GMU.mason_campus_2005_roads"
  ],
  "gbl_mdVersion_s": "1.0",
  "dct_temporal_sm": [
    "2005-01-01 01:01:01+00:00"
  ],
  "dct_spatial_sm": [
    "George Mason University"
  ],
  "dct_references_s": "{\"http://www.opengis.net/def/serviceType/ogc/wfs\":\"https://gmutantt.gmu.edu/geoserver/GMUGeodata/wfs\",\"http://www.opengis.net/def/serviceType/ogc/wms\":\"https://gmutantt.gmu.edu/geoserver/GMUGeodata/wms\"}"
}